setup.cfg
setup.py
funkyserver/__init__.py
funkyserver.egg-info/PKG-INFO
funkyserver.egg-info/SOURCES.txt
funkyserver.egg-info/dependency_links.txt
funkyserver.egg-info/top_level.txt