Metadata-Version: 1.0
Name: funkyserver
Version: 0.1
Summary: FunkyServer is simple package to create Flask servers in background processes.
Home-page: http://github.com/andyalky/funkyserver
Author: Andrew Alkhouri
Author-email: andy@alky.co
License: MIT
Platform: UNKNOWN
